src/__init__.py
src/arealuis.py
arealuis-0.0.1.dist-info/LICENSE
arealuis-0.0.1.dist-info/METADATA
arealuis-0.0.1.dist-info/WHEEL
arealuis-0.0.1.dist-info/top_level.txt
arealuis-0.0.1.dist-info/RECORD
