Metadata-Version: 2.1
Name: arealuis
Version: 0.0.1
Summary: meu primeiro pacote
Author: Luis Eduardo
Author-email: le1307114@gmail.com
Keywords: python,first package
Classifier: Development Status :: 3 - Alpha
Classifier: Intended Audience :: Education
Classifier: Programming Language :: Python :: 3
Classifier: Operating System :: OS Independent
License-File: LICENSE
